{"type": "Experiment", "sample": {"type": "Stack", "layers": [{"name": "Silicon", "type": "Slab", "thickness": {"type": "Parameter", "name": "Silicon thickness", "value": 0.0, "fixed": true, "fittable": true, "bounds": {"type": "Bounded", "limits": [0.0, 100.0]}}, "interface": {"type": "Parameter", "name": "Silicon interface", "value": 15.705500351400659, "fixed": false, "fittable": true, "bounds": {"type": "Bounded", "limits": [8.65, 28.65]}}, "material": {"type": "SLD", "name": "Silicon", "rho": {"type": "Parameter", "name": "Silicon rho", "value": 20.07, "fixed": true, "fittable": true, "bounds": {"type": "Bounded", "limits": [19.07, 21.07]}}, "irho": {"type": "Parameter", "name": "Silicon irho", "value": 0.458, "fixed": true, "fittable": true, "bounds": {"type": "Bounded", "limits": [-0.542, 1.458]}}}}, {"name": "SiOx", "type": "Slab", "thickness": {"type": "Parameter", "name": "SiOx thickness", "value": 35.896357930790835, "fixed": false, "fittable": true, "bounds": {"type": "Bounded", "limits": [0.0, 140.55]}}, "interface": {"type": "Parameter", "name": "SiOx interface", "value": 3.183570801327369, "fixed": false, "fittable": true, "bounds": {"type": "Bounded", "limits": [0.0, 13.224]}}, "material": {"type": "SLD", "name": "SiOx", "rho": {"type": "Parameter", "name": "SiOx rho", "value": 32.944751043083436, "fixed": false, "fittable": true, "bounds": {"type": "Bounded", "limits": [32.94, 34.94]}}, "irho": {"type": "Parameter", "name": "SiOx irho", "value": 6.16963762555678, "fixed": false, "fittable": true, "bounds": {"type": "Bounded", "limits": [5.871, 7.871]}}}}, {"name": "Permalloy", "type": "Slab", "thickness": {"type": "Parameter", "name": "Permalloy thickness", "value": 106.93096812494208, "fixed": false, "fittable": true, "bounds": {"type": "Bounded", "limits": [8.0, 208.0]}}, "interface": {"type": "Parameter", "name": "Permalloy interface", "value": 9.784682610300655, "fixed": false, "fittable": true, "bounds": {"type": "Bounded", "limits": [0.0, 16.751]}}, "material": {"type": "SLD", "name": "Permalloy", "rho": {"type": "Parameter", "name": "Permalloy rho", "value": 65.51780766477388, "fixed": false, "fittable": true, "bounds": {"type": "Bounded", "limits": [65.49, 67.49]}}, "irho": {"type": "Parameter", "name": "Permalloy irho", "value": -0.04570065281135156, "fixed": false, "fittable": true, "bounds": {"type": "Bounded", "limits": [-1.0, 1.0]}}}}, {"name": "Interace", "type": "Slab", "thickness": {"type": "Parameter", "name": "Interace thickness", "value": 1.3141656633028755, "fixed": false, "fittable": true, "bounds": {"type": "Bounded", "limits": [0.0, 110.0]}}, "interface": {"type": "Parameter", "name": "Interace interface", "value": 5.157005546323306, "fixed": false, "fittable": true, "bounds": {"type": "Bounded", "limits": [0.0, 16.751]}}, "material": {"type": "SLD", "name": "Interace", "rho": {"type": "Parameter", "name": "Interace rho", "value": 99.05799655012052, "fixed": false, "fittable": true, "bounds": {"type": "Bounded", "limits": [99.0, 101.0]}}, "irho": {"type": "Parameter", "name": "Interace irho", "value": 4.712505862662254, "fixed": false, "fittable": true, "bounds": {"type": "Bounded", "limits": [2.75, 4.75]}}}}, {"name": "Platinum", "type": "Slab", "thickness": {"type": "Parameter", "name": "Platinum thickness", "value": 49.28629292214989, "fixed": false, "fittable": true, "bounds": {"type": "Bounded", "limits": [0.0, 149.49]}}, "interface": {"type": "Parameter", "name": "Platinum interface", "value": 3.6628409510428446, "fixed": false, "fittable": true, "bounds": {"type": "Bounded", "limits": [0.0, 13.657]}}, "material": {"type": "SLD", "name": "Platinum", "rho": {"type": "Parameter", "name": "Platinum rho", "value": 134.8993290775315, "fixed": false, "fittable": true, "bounds": {"type": "Bounded", "limits": [132.9, 134.9]}}, "irho": {"type": "Parameter", "name": "Platinum irho", "value": 8.448836295112862, "fixed": false, "fittable": true, "bounds": {"type": "Bounded", "limits": [6.451, 8.451]}}}}, {"name": "Air", "type": "Slab", "thickness": {"type": "Parameter", "name": "Air thickness", "value": 0.0, "fixed": true, "fittable": true, "bounds": {"type": "Bounded", "limits": [0.0, 100.0]}}, "interface": {"type": "Parameter", "name": "Air interface", "value": 0.0, "fixed": true, "fittable": true, "bounds": {"type": "Unbounded", "limits": [0, Infinity]}}, "material": {"type": "SLD", "name": "Air", "rho": {"type": "Parameter", "name": "Air rho", "value": 0.0, "fixed": true, "fittable": true, "bounds": {"type": "Bounded", "limits": [-1.0, 1.0]}}, "irho": {"type": "Parameter", "name": "Air irho", "value": 0.0, "fixed": true, "fittable": true, "bounds": {"type": "Bounded", "limits": [-1.0, 1.0]}}}}]}, "probe": {"type": "XrayProbe", "intensity": {"type": "Parameter", "name": "intensity R1XRR", "value": 1.0193593052616856, "fixed": false, "fittable": true, "bounds": {"type": "Bounded", "limits": [0.95, 1.05]}}, "background": {"type": "Parameter", "name": "background R1XRR", "value": 0, "fixed": true, "fittable": true, "bounds": {"type": "Unbounded", "limits": [0.0, Infinity]}}, "back_absorption": {"type": "Parameter", "name": "back_absorption R1XRR", "value": 1, "fixed": true, "fittable": true, "bounds": {"type": "Unbounded", "limits": [0.0, 1.0]}}, "theta_offset": {"type": "Parameter", "name": "theta_offset R1XRR", "value": 0, "fixed": true, "fittable": true, "bounds": {"type": "Unbounded", "limits": [-Infinity, Infinity]}}, "sample_broadening": {"type": "Parameter", "name": "sample_broadening R1XRR", "value": 0, "fixed": true, "fittable": true, "bounds": {"type": "Unbounded", "limits": [-Infinity, Infinity]}}}, "roughness_limit": 0, "dz": 1, "dA": null, "step_interfaces": false, "interpolation": 0, "name": "R1XRR", "refl1d": "0.8.9"}